koya_normalization/__init__.py
koya_normalization/koya_normalization.py
koya_normalization-0.0.3.dist-info/LICENSE
koya_normalization-0.0.3.dist-info/METADATA
koya_normalization-0.0.3.dist-info/WHEEL
koya_normalization-0.0.3.dist-info/top_level.txt
koya_normalization-0.0.3.dist-info/RECORD
