Metadata-Version: 2.1
Name: koya-normalization
Version: 0.0.3
Author: 
Author-email: 
License: MIT
Requires-Python: >=3.6
License-File: LICENSE
Requires-Dist: pandas
Requires-Dist: gspread
Requires-Dist: df2gspread
